tomato_jumo/__init__.py
tomato_jumo-2.1.0.dist-info/licenses/LICENSE
tomato_jumo-2.1.0.dist-info/METADATA
tomato_jumo-2.1.0.dist-info/WHEEL
tomato_jumo-2.1.0.dist-info/top_level.txt
tomato_jumo-2.1.0.dist-info/RECORD
